mkdocs_bootstrap/__init__.py
mkdocs_bootstrap/mkdocs_theme.yml
mkdocs_bootstrap/css/base.css
mkdocs_bootstrap/css/bootstrap.min.css
mkdocs_bootstrap-1.1.1.dist-info/LICENSE
mkdocs_bootstrap-1.1.1.dist-info/METADATA
mkdocs_bootstrap-1.1.1.dist-info/WHEEL
mkdocs_bootstrap-1.1.1.dist-info/entry_points.txt
mkdocs_bootstrap-1.1.1.dist-info/top_level.txt
mkdocs_bootstrap-1.1.1.dist-info/RECORD
