Metadata-Version: 1.2
Name: mkdocs-bootstrap
Version: 1.1.1
Summary: Bootstrap theme for MkDocs
Home-page: http://mkdocs.github.io/mkdocs-bootstrap/
Author: Dougal Matthews
Author-email: dougal@dougalmatthews.com
License: BSD
Platform: UNKNOWN
Requires-Python: >=3.5
